liteocr/__init__.py
liteocr/ocr.py
liteocr/ocr_demo.py
liteocr/run_ocr.py
liteocr-0.2.1.dist-info/DESCRIPTION.rst
liteocr-0.2.1.dist-info/METADATA
liteocr-0.2.1.dist-info/RECORD
liteocr-0.2.1.dist-info/WHEEL
liteocr-0.2.1.dist-info/entry_points.txt
liteocr-0.2.1.dist-info/metadata.json
liteocr-0.2.1.dist-info/top_level.txt
