Metadata-Version: 1.1
Name: liteocr
Version: 0.2.1
Summary: Light-weight OCR engine.
Home-page: http://github.com/LinxiFan/LiteOCR
Author: Linxi (Jim) Fan
Author-email: jimfan@cs.stanford.edu
License: GPLv3
Keywords: OCR image recognition Tesseract
Platform: UNKNOWN
Classifier: Development Status :: 4 - Beta
Classifier: Topic :: Scientific/Engineering :: Image Recognition
Classifier: Topic :: Utilities
Classifier: Environment :: Console
Classifier: Programming Language :: Python :: 3
